fxrt/__init__.py
fxrt/broker.py
fxrt/rc4.py
fxrt-1.2.dist-info/METADATA
fxrt-1.2.dist-info/WHEEL
fxrt-1.2.dist-info/top_level.txt
fxrt-1.2.dist-info/RECORD
