Metadata-Version: 2.1
Name: fxrt
Version: 1.2
Summary: Realtime FX prices
Home-page: UNKNOWN
Author: Philippe Remy
License: MIT
Platform: UNKNOWN
Requires-Dist: requests
